timmins/__init__.py
timmins/__main__.py
timmins-1.0.0.dist-info/METADATA
timmins-1.0.0.dist-info/WHEEL
timmins-1.0.0.dist-info/entry_points.txt
timmins-1.0.0.dist-info/top_level.txt
timmins-1.0.0.dist-info/RECORD
