Metadata-Version: 2.1
Name: timmins
Version: 1.0.0
Summary: Python packaging using setup.py
Author: Mohammad Mahfooz Alam
Author-email: mahfooz.iiitian@gmail.com
